shopee_crawler/__init__.py
shopee_crawler/crawler.py
shopee_crawler/toolkit/__init__.py
shopee_crawler/toolkit/crawl_by_cat_url.py
shopee_crawler/toolkit/crawl_by_shop_url.py
shopee_crawler/toolkit/curl.py
shopee_crawler_pkg_lthoangg-0.1.1.dist-info/METADATA
shopee_crawler_pkg_lthoangg-0.1.1.dist-info/WHEEL
shopee_crawler_pkg_lthoangg-0.1.1.dist-info/top_level.txt
shopee_crawler_pkg_lthoangg-0.1.1.dist-info/RECORD
